ray_skorch/__init__.py
ray_skorch/base.py
ray_skorch/dataset.py
ray_skorch/docs.py
ray_skorch/utils.py
ray_skorch/callbacks/__init__.py
ray_skorch/callbacks/constants.py
ray_skorch/callbacks/skorch.py
ray_skorch/callbacks/train.py
ray_skorch/callbacks/utils.py
ray_skorch-0.0.3.dist-info/LICENSE
ray_skorch-0.0.3.dist-info/METADATA
ray_skorch-0.0.3.dist-info/WHEEL
ray_skorch-0.0.3.dist-info/top_level.txt
ray_skorch-0.0.3.dist-info/RECORD
