Metadata-Version: 2.1
Name: ray-skorch
Version: 0.0.3
Summary: Skorch on Ray Train
Home-page: https://github.com/Yard1/ray-skorch
Author: Antoni Baum & contributors
Author-email: antoni.baum@protonmail.com
License: UNKNOWN
Platform: UNKNOWN
License-File: LICENSE
Requires-Dist: ray[data,default] (>=1.11.0)
Requires-Dist: torch
Requires-Dist: pandas
Requires-Dist: skorch (==0.11.0)
